pginter/__init__.py
pginter/_pg_root.py
pginter/icon.png
pginter/theme/__init__.py
pginter/theme/_manager.py
pginter/theme/themes/default.json
pginter/types/__init__.py
pginter/types/_better_dict.py
pginter/types/_binds.py
pginter/types/_color.py
pginter/types/_constants.py
pginter/types/_geo_types.py
pginter/types/_notifications.py
pginter/types/_scheme.py
pginter/types/_style.py
pginter/types/_tk_vars.py
pginter/utils/__init__.py
pginter/utils/_funcs.py
pginter/utils/_image_funcs.py
pginter/widgets/__init__.py
pginter/widgets/_button.py
pginter/widgets/_entry.py
pginter/widgets/_frame.py
pginter/widgets/_geo_manager.py
pginter/widgets/_label.py
pginter/widgets/_supports_children.py
pginter/widgets/_surface_frame.py
pginter-0.2.16.dist-info/LICENSE
pginter-0.2.16.dist-info/METADATA
pginter-0.2.16.dist-info/WHEEL
pginter-0.2.16.dist-info/top_level.txt
pginter-0.2.16.dist-info/RECORD
