Metadata-Version: 2.1
Name: pginter
Version: 0.2.16
Summary: A python GUI interface, based on pygame
Home-page: https://github.com/Nilusink/PgInter
Author: Nilusink
Author-email: nilusink@protonmail.com
Classifier: Programming Language :: Python :: 3.12
Classifier: License :: OSI Approved :: MIT License
Classifier: Operating System :: OS Independent
Requires-Python: >=3.11
License-File: LICENSE
Requires-Dist: setuptools >=60.2.0
Requires-Dist: pygame >=2.1.2
